{
  "actions": [
    {
      "id": "set_silent_mode",
      "title": {
        "en": "Set Silent Mode",
        "nl": "Stel Stille Modus in",
        "de": "Leiser Modus einstellen",
        "fr": "Définir Mode Silencieux",
        "it": "Imposta Modalità Silenziosa",
        "es": "Establecer Modo Silencioso",
        "da": "Indstil Stille tilstand",
        "no": "Sett Stillemodus",
        "sv": "Ställ in Tyst läge",
        "fi": "Aseta Hiljainen Tila",
        "pl": "Ustaw Tryb Cichy",
        "cs": "Nastavit Tichý Režim",
        "sk": "Nastaviť Tichý Režim",
        "hu": "Csendes Üzemmód beállítása",
        "pt": "Definir Modo Silencioso",
        "ro": "Setare Mod Silențios"
      },
      "args": [
        {
          "name": "silent_mode",
          "type": "checkbox",
          "values": [
            {
              "id": "true",
              "title": {
                "en": "On",
                "nl": "Aan",
                "de": "An",
                "fr": "Activé",
                "it": "Attiva",
                "es": "Activado",
                "da": "Til",
                "no": "På",
                "sv": "På",
                "fi": "Päällä",
                "pl": "Włączony",
                "cs": "Zapnutý",
                "sk": "Zapnutý",
                "hu": "Bekapcsolva",
                "pt": "Ativado",
                "ro": "Pornit"
              }
            },
            {
              "id": "false",
              "title": {
                "en": "Off",
                "nl": "Uit",
                "de": "Aus",
                "fr": "Désactivé",
                "it": "Disattivata",
                "es": "Desactivado",
                "da": "Fra",
                "no": "Av",
                "sv": "Av",
                "fi": "Pois",
                "pl": "Wyłączony",
                "cs": "Vypnutý",
                "sk": "Vypnutý",
                "hu": "Kikapcsolva",
                "pt": "Desativado",
                "ro": "Oprit"
              }
            }
          ]
        }
      ]
    },
    {
      "id": "turn_silent_mode_on",
      "title": {
        "en": "Turn Silent Mode on",
        "nl": "Zet Stille Modus aan",
        "de": "Leiser Modus einschalten",
        "fr": "Activer Mode Silencieux",
        "it": "Attiva Modalità Silenziosa",
        "es": "Activar Modo Silencioso",
        "da": "Tænd for Stille tilstand",
        "no": "Slå på Stillemodus",
        "sv": "Sätt på Tyst läge",
        "fi": "Kytke Hiljainen Tila päälle",
        "pl": "Włącz Tryb Cichy",
        "cs": "Zapnout Tichý Režim",
        "sk": "Zapnúť Tichý Režim",
        "hu": "Csendes Üzemmód bekapcsolása",
        "pt": "Ativar Modo Silencioso",
        "ro": "Pornește Mod Silențios"
      },
      "args": []
    },
    {
      "id": "turn_silent_mode_off",
      "title": {
        "en": "Turn Silent Mode off",
        "nl": "Zet Stille Modus uit",
        "de": "Leiser Modus ausschalten",
        "fr": "Désactiver Mode Silencieux",
        "it": "Disattiva Modalità Silenziosa",
        "es": "Desactivar Modo Silencioso",
        "da": "Sluk for Stille tilstand",
        "no": "Slå av Stillemodus",
        "sv": "Stäng av Tyst läge",
        "fi": "Kytke Hiljainen Tila pois",
        "pl": "Wyłącz Tryb Cichy",
        "cs": "Vypnout Tichý Režim",
        "sk": "Vypnúť Tichý Režim",
        "hu": "Csendes Üzemmód kikapcsolása",
        "pt": "Desativar Modo Silencioso",
        "ro": "Oprește Mod Silențios"
      },
      "args": []
    },
    {
      "id": "thermostat_mode_set",
      "title": {
        "en": "Set the mode",
        "nl": "Stel de modus in",
        "de": "Modus setzen",
        "fr": "Définir le mode",
        "it": "Imposta la modalità",
        "sv": "Ställ in läget",
        "no": "Innstill modusen",
        "es": "Configurar el modo",
        "da": "Indstil tilstanden",
        "ru": "Установить режим",
        "pl": "Ustaw tryb",
        "ko": "모드 설정"
      },
      "args": [
        {
          "name": "thermostat_mode",
          "type": "dropdown",
          "values": [
            {
              "id": "auto",
              "title": {
                "en": "Automatic",
                "nl": "Automatisch",
                "de": "Automatisch",
                "fr": "Automatique",
                "it": "Automatica",
                "sv": "Automatiskt",
                "no": "Automatisk",
                "es": "Automático",
                "da": "Automatisk",
                "ru": "Автоматически",
                "pl": "Automatyczny",
                "ko": "자동"
              }
            },
            {
              "id": "heat",
              "title": {
                "en": "Heat",
                "nl": "Verhitten",
                "de": "Heizen",
                "fr": "Chauffer",
                "it": "Calore",
                "sv": "Värme",
                "no": "Varme",
                "es": "Calentar",
                "da": "Opvarm",
                "ru": "Обогрев",
                "pl": "Ogrzewanie",
                "ko": "난방"
              }
            },
            {
              "id": "cool",
              "title": {
                "en": "Cool",
                "nl": "Koelen",
                "de": "Kühlen",
                "fr": "Refroidir",
                "it": "Raffreddamento",
                "sv": "Kyla",
                "no": "Avkjøle",
                "es": "Enfriar",
                "da": "Køl ned",
                "ru": "Охлаждение",
                "pl": "Chłodzenie",
                "ko": "냉방"
              }
            }
          ]
        }
      ]
    },
    {
      "id": "set_max_fan_speed",
      "title": {
        "en": "Set the maximal fan speed to",
        "nl": "De maximale ventilatorsnelheid instellen op",
        "da": "Indstil den maksimale ventilatorhastighed til",
        "it": "Imposta la velocità massima della ventola su",
        "ko": "최대 팬 속도를 다음으로 설정",
        "no": "Sett maksimal viftehastighet til",
        "pl": "Ustaw maksymalną prędkość wentylatora na",
        "ru": "Установить максимальную скорость вентилятора на",
        "sv": "Ställ in maximal fläkthastighet på",
        "es": "Ajustar la velocidad máxima del ventilador a",
        "fr": "Définir la vitesse maximale de ventilation sur"
      },
      "args": [
        {
          "name": "fan_speed",
          "type": "range",
          "min": 300,
          "max": 900,
          "step": 50,
          "value": 500,
          "label": "rpm",
          "labelDecimals": 0
        }
      ]
    },
    {
      "id": "set_min_fan_speed",
      "title": {
        "en": "Set the minimum fan speed to",
        "nl": "De minimale ventilatorsnelheid instellen op",
        "da": "Indstil den minimale ventilatorhastighed til",
        "it": "Imposta la velocità minima della ventola su",
        "ko": "최소 팬 속도를 다음으로 설정",
        "no": "Sett minimal viftehastighet til",
        "pl": "Ustaw minimalną prędkość wentylatora na",
        "ru": "Установить минимальную скорость вентилятора на",
        "sv": "Ställ in minimal fläkthastighet på",
        "es": "Ajustar la velocidad mínima del ventilador a",
        "fr": "Définir la vitesse minimale de ventilation sur"
      },
      "args": [
        {
          "name": "fan_speed",
          "type": "range",
          "min": 300,
          "max": 900,
          "step": 50,
          "value": 500,
          "label": "rpm",
          "labelDecimals": 0
        }
      ]
    },
    {
      "id": "set_max_frequency_in_heating_mode",
      "title": {
        "en": "Set the maximal compressor frequency in heating mode to",
        "nl": "De maximale compressorfrequentie in verwarmingsmodus instellen op",
        "de": "Maximale Kompressorfrequenz im Heizmodus einstellen auf",
        "fr": "Définir la fréquence maximale du compresseur en mode chauffage sur",
        "it": "Imposta la frequenza massima del compressore in modalità riscaldamento su",
        "es": "Ajustar la frecuencia máxima del compresor en modo calefacción a",
        "da": "Indstil den maksimale kompressorfrekvens i varmetilstand til",
        "no": "Still inn maksimal kompressorfrekvens i varmemodus til",
        "sv": "Ställ in maximal kompressorfrekvens i värmeläge på",
        "fi": "Aseta maksimikompressoritaajuus lämmitystilassa arvoon",
        "pl": "Ustaw maksymalną częstotliwość sprężarki w trybie ogrzewania na",
        "cs": "Nastavit maximální frekvenci kompresoru v režimu vytápění na",
        "sk": "Nastaviť maximálnu frekvenciu kompresora v režime vykurovania na",
        "hu": "Állítsa be a maximális kompresszorfrekvenciát fűtési módban",
        "pt": "Definir a frequência máxima do compressor no modo de aquecimento para",
        "ro": "Setați frecvența maximă a compresorului în modul de încălzire la"
      },
      "args": [
        {
          "name": "maximal_frequency_in_heating_mode",
          "type": "range",
          "min": 20,
          "max": 60,
          "step": 5,
          "value": 50,
          "label": "Hz",
          "labelDecimals": 0
        }
      ]
    }

  ],
  "triggers": [
    {
      "id": "thermostat_mode_changed",
      "title": {
        "en": "Thermostat mode has changed",
        "nl": "Thermostaat modus is veranderd",
        "de": "Thermostat-Modus hat sich geändert",
        "fr": "Mode thermostat a été modifié",
        "it": "La modalità del termostato è cambiata",
        "sv": "Termostatläge ändrades",
        "no": "Termostatmodus ble endret",
        "es": "El modo del termostato ha cambiado",
        "da": "Termostattilstand er blevet ændret",
        "ru": "Режим термостата изменен",
        "pl": "Zmiana trybu termostatu",
        "ko": "온도조절기 모드 변경됨"
      },
      "args": [
        {
          "name": "thermostat_mode",
          "type": "dropdown",
          "values": [
            {
              "id": "auto",
              "title": {
                "en": "Automatic",
                "nl": "Automatisch",
                "de": "Automatisch",
                "fr": "Automatique",
                "it": "Automatica",
                "sv": "Automatiskt",
                "no": "Automatisk",
                "es": "Automático",
                "da": "Automatisk",
                "ru": "Автоматически",
                "pl": "Automatyczny",
                "ko": "자동"
              }
            },
            {
              "id": "heat",
              "title": {
                "en": "Heat",
                "nl": "Verhitten",
                "de": "Heizen",
                "fr": "Chauffer",
                "it": "Calore",
                "sv": "Värme",
                "no": "Varme",
                "es": "Calentar",
                "da": "Opvarm",
                "ru": "Обогрев",
                "pl": "Ogrzewanie",
                "ko": "난방"
              }
            },
            {
              "id": "cool",
              "title": {
                "en": "Cool",
                "nl": "Koelen",
                "de": "Kühlen",
                "fr": "Refroidir",
                "it": "Raffreddamento",
                "sv": "Kyla",
                "no": "Avkjøle",
                "es": "Enfriar",
                "da": "Køl ned",
                "ru": "Охлаждение",
                "pl": "Chłodzenie",
                "ko": "냉방"
              }
            }
          ]
        }
      ]
    },
    {
      "id": "fan_speed_changed",
      "title": {
        "en": "The fan speed changed",
        "nl": "De ventilatorsnelheid is veranderd",
        "da": "Ventilatorhastigheden ændrede sig",
        "it": "La velocità della ventola è cambiata",
        "ko": "팬 속도가 변경되면",
        "no": "Viftehastigheten ble endret",
        "pl": "Prędkość wentylatora zmieniła się",
        "ru": "Скорость вентилятора изменена",
        "sv": "Fläkthastigheten ändrades",
        "es": "La velocidad del ventilador ha cambiado",
        "fr": "La vitesse de ventilation a changé"
      },
      "tokens": [
        {
          "name": "fan_speed",
          "title": {
            "en": "Fan Speed",
            "nl": "Ventilatorsnelheid",
            "da": "Ventilatorhastighed",
            "it": "Velocità della ventola",
            "ko": "팬 속도",
            "no": "Viftehastighet",
            "pl": "Prędkość wentylatora",
            "ru": "Скорость вентилятора",
            "sv": "Fläkthastighet",
            "es": "Velocidad del ventilador",
            "fr": "Vitesse de ventilation"
          },
          "type": "number",
          "example": 0.5
        }
      ]
    }

  ],
  "conditions": [
    {
      "id": "thermostat_mode_is",
      "title": {
        "en": "Thermostat mode !{{is|is not}}",
        "nl": "Thermostaat modus !{{is|is niet}}",
        "de": "Thermostat-Modus !{{ist|ist nicht}}",
        "fr": "Mode thermostat !{{est|n'est pas}}",
        "it": "La modalità del termostato !{{è|non è}}",
        "sv": "Termostatläge !{{är|är inte}}",
        "no": "Termostatmodus !{{er|er ikke}}",
        "es": "El modo del termostato !{{está|no está}}",
        "da": "Termostattilstand !{{er|er ikke}}",
        "pl": "Tryb termostatu !{{to|to nie}}"
      },
      "args": [
        {
          "name": "thermostat_mode",
          "type": "dropdown",
          "values": [
            {
              "id": "auto",
              "title": {
                "en": "Automatic",
                "nl": "Automatisch",
                "de": "Automatisch",
                "fr": "Automatique",
                "it": "Automatica",
                "sv": "Automatiskt",
                "no": "Automatisk",
                "es": "Automatico",
                "da": "Automatisk",
                "pl": "Automatyczny"
              }
            },
            {
              "id": "heat",
              "title": {
                "en": "Heat",
                "nl": "Verhitten",
                "de": "Heizen",
                "fr": "Chauffer",
                "it": "Calore",
                "sv": "Värme",
                "no": "Varme",
                "es": "Calentar",
                "da": "Opvarm",
                "pl": "Ogrzewanie"
              }
            },
            {
              "id": "cool",
              "title": {
                "en": "Cool",
                "nl": "Koelen",
                "de": "Kühlen",
                "fr": "Refroidir",
                "it": "Raffreddamento",
                "sv": "Kyla",
                "no": "Avkjøle",
                "es": "Enfriar",
                "da": "Køl ned",
                "pl": "Chłodzenie"
              }
            }
          ]
        }
      ]
    }
  ]
}
